cornserve/__init__.py
cornserve/constants.py
cornserve/frontend.py
cornserve/logging.py
cornserve/tracing.py
cornserve/utils.py
cornserve/app/__init__.py
cornserve/app/base.py
cornserve/cli/__init__.py
cornserve/cli/audio_streamer.py
cornserve/cli/log_streamer.py
cornserve/cli/main.py
cornserve/cli/tasklib_explorer.py
cornserve/cli/utils/__init__.py
cornserve/cli/utils/k8s.py
cornserve/services/__init__.py
cornserve/services/resource.py
cornserve/services/utils.py
cornserve/services/gateway/__init__.py
cornserve/services/gateway/entrypoint.py
cornserve/services/gateway/models.py
cornserve/services/gateway/router.py
cornserve/services/gateway/session.py
cornserve/services/gateway/task_manager.py
cornserve/services/gateway/app/manager.py
cornserve/services/gateway/app/models.py
cornserve/services/pb/common_pb2.py
cornserve/services/pb/common_pb2.pyi
cornserve/services/pb/common_pb2_grpc.py
cornserve/services/pb/resource_manager_pb2.py
cornserve/services/pb/resource_manager_pb2.pyi
cornserve/services/pb/resource_manager_pb2_grpc.py
cornserve/services/pb/sidecar_pb2.py
cornserve/services/pb/sidecar_pb2.pyi
cornserve/services/pb/sidecar_pb2_grpc.py
cornserve/services/pb/task_dispatcher_pb2.py
cornserve/services/pb/task_dispatcher_pb2.pyi
cornserve/services/pb/task_dispatcher_pb2_grpc.py
cornserve/services/pb/task_manager_pb2.py
cornserve/services/pb/task_manager_pb2.pyi
cornserve/services/pb/task_manager_pb2_grpc.py
cornserve/services/resource_manager/__init__.py
cornserve/services/resource_manager/entrypoint.py
cornserve/services/resource_manager/grpc.py
cornserve/services/resource_manager/manager.py
cornserve/services/sidecar/__init__.py
cornserve/services/sidecar/launch.py
cornserve/services/sidecar/receiver.py
cornserve/services/sidecar/scheduler.py
cornserve/services/sidecar/schema.py
cornserve/services/sidecar/sender.py
cornserve/services/sidecar/server.py
cornserve/services/sidecar/shm_manager.py
cornserve/services/task_dispatcher/__init__.py
cornserve-0.1.0.dist-info/METADATA
cornserve-0.1.0.dist-info/WHEEL
cornserve-0.1.0.dist-info/entry_points.txt
cornserve-0.1.0.dist-info/top_level.txt
cornserve-0.1.0.dist-info/RECORD
